unireport/__init__.py
unireport/exceptions.py
unireport/logger.py
unireport/plugin.py
unireport/renderer.py
unireport/plugins/__init__.py
unireport/plugins/builtin.py
unireport/plugins/external/__init__.py
unireport/plugins/external/grafana/__init__.py
unireport/plugins/external/grafana/api.py
unireport/plugins/external/grafana/client.py
unireport/plugins/external/grafana/plugin.py
unireport-0.0.9.dist-info/METADATA
unireport-0.0.9.dist-info/WHEEL
unireport-0.0.9.dist-info/licenses/LICENSE
unireport-0.0.9.dist-info/RECORD
