Metadata-Version: 2.3
Name: unireport
Version: 0.0.9
Dynamic: Description
Dynamic: Description-Content-Type
Summary: Generate reports by template for lots of different external services
Project-URL: Homepage, https://github.com/zifter/unireport
Project-URL: Source, https://github.com/zifter/unireport
Project-URL: Tracker, https://github.com/zifter/unireport/issues
Author-email: Aleh Strakachuk <zifter.ai+unireport@gmail.com>
License: MIT
License-File: LICENSE
Keywords: backend,engine,grafana,report,template
Classifier: Intended Audience :: Developers
Classifier: Programming Language :: Python
Classifier: Programming Language :: Python :: 3.10
Classifier: Programming Language :: Python :: 3.11
Requires-Python: <4,>=3.10
Requires-Dist: jinja2>=3.1
Requires-Dist: requests>=2.23.0
Provides-Extra: testing
Requires-Dist: parameterized==0.9.0; extra == 'testing'
Requires-Dist: pytest-cov==4.1.0; extra == 'testing'
Requires-Dist: pytest-rerunfailures==13.0; extra == 'testing'
Requires-Dist: pytest-timeout==2.1.0; extra == 'testing'
Requires-Dist: pytest==7.4.1; extra == 'testing'
